BuildSystem/retrieval.py
BuildSystem/args.py
BuildSystem/sourceDatabase.py
BuildSystem/script.py
BuildSystem/configure.py
BuildSystem/RDict.py
BuildSystem/pythonpath.py
BuildSystem/logger.py
BuildSystem/urlMappingLocal.py
BuildSystem/urlMappingInstalled.py
BuildSystem/maker.py
BuildSystem/graph.py
BuildSystem/make.py
BuildSystem/__init__.py
BuildSystem/nargs.py
BuildSystem/help.py
BuildSystem/regression/__init__.py
BuildSystem/regression/testCase.py
BuildSystem/config/types.py
BuildSystem/config/package.py
BuildSystem/config/headers.py
BuildSystem/config/libraries.py
BuildSystem/config/framework.py
BuildSystem/config/preTests.py
BuildSystem/config/util.py
BuildSystem/config/atomics.py
BuildSystem/config/setCompilers.py
BuildSystem/config/compilerFlags.py
BuildSystem/config/__init__.py
BuildSystem/config/setsOrdered.py
BuildSystem/config/compilerOptions.py
BuildSystem/config/python.py
BuildSystem/config/programs.py
BuildSystem/config/setsBackport.py
BuildSystem/config/compilers.py
BuildSystem/config/sourceControl.py
BuildSystem/config/functions.py
BuildSystem/config/base.py
BuildSystem/config/packages/scalapack.py
BuildSystem/config/packages/PTScotch.py
BuildSystem/config/packages/Numpy.py
BuildSystem/config/packages/MUMPS.py
BuildSystem/config/packages/concurrencykit.py
BuildSystem/config/packages/hypre.py
BuildSystem/config/packages/tchem.py
BuildSystem/config/packages/papi.py
BuildSystem/config/packages/Matlab.py
BuildSystem/config/packages/c2html.py
BuildSystem/config/packages/ctetgen.py
BuildSystem/config/packages/exodusii.py
BuildSystem/config/packages/Mathematica.py
BuildSystem/config/packages/boost.py
BuildSystem/config/packages/X.py
BuildSystem/config/packages/SuperLU_DIST.py
BuildSystem/config/packages/BlasLapack.py
BuildSystem/config/packages/metis.py
BuildSystem/config/packages/MPICH.py
BuildSystem/config/packages/amanzi.py
BuildSystem/config/packages/parmetis.py
PETSc_BS-0.0.0.dev1.dist-info/METADATA
PETSc_BS-0.0.0.dev1.dist-info/WHEEL
PETSc_BS-0.0.0.dev1.dist-info/entry_points.txt
PETSc_BS-0.0.0.dev1.dist-info/top_level.txt
PETSc_BS-0.0.0.dev1.dist-info/metadata.json
PETSc_BS-0.0.0.dev1.dist-info/DESCRIPTION.rst
PETSc_BS-0.0.0.dev1.dist-info/RECORD
