Metadata-Version: 2.0
Name: PETSc-BS
Version: 0.0.0.dev1
Summary: Packages for PETSc BuildSystem
Home-page: UNKNOWN
Author: Elijah DeLee
Author-email: deleeke@gmail.com
License: MIT
Keywords: C++ build system
Platform: UNKNOWN
Classifier: Development Status :: 3 - Alpha
Classifier: License :: OSI Approved :: MIT License
Classifier: Programming Language :: Python :: 2
Classifier: Programming Language :: Python :: 2.7
Requires-Dist: os
Requires-Dist: sys
Provides-Extra: dev
Requires-Dist: check-manifest; extra == 'dev'
